kbatch_proxy/__init__.py
kbatch_proxy/main.py
kbatch_proxy/patch.py
kbatch_proxy/utils.py
tests/__init__.py
tests/test_app.py
tests/test_proxy.py
tests/test_w_k8s.py
kbatch_proxy-0.4.2.dist-info/METADATA
kbatch_proxy-0.4.2.dist-info/WHEEL
kbatch_proxy-0.4.2.dist-info/entry_points.txt
kbatch_proxy-0.4.2.dist-info/top_level.txt
kbatch_proxy-0.4.2.dist-info/RECORD
