Metadata-Version: 2.1
Name: kbatch-proxy
Version: 0.4.2
Summary: Proxy batch job requests to kubernetes.
Home-page: https://github.com/kbatch-dev/kbatch
Author: Tom Augspurger
Author-email: taugspurger@microsoft.com
Requires-Dist: escapism
Requires-Dist: fastapi
Requires-Dist: httpx
Requires-Dist: jupyterhub
Requires-Dist: kubernetes
Requires-Dist: pydantic[dotenv] <2.0.0
Provides-Extra: all
Requires-Dist: pytest ; extra == 'all'
Requires-Dist: pytest-mock ; extra == 'all'
Requires-Dist: uvicorn[standard] ; extra == 'all'
Requires-Dist: gunicorn ==20.1.0 ; extra == 'all'
Requires-Dist: rich ; extra == 'all'
Provides-Extra: dev
Requires-Dist: uvicorn[standard] ; extra == 'dev'
Requires-Dist: gunicorn ==20.1.0 ; extra == 'dev'
Requires-Dist: rich ; extra == 'dev'
Provides-Extra: test
Requires-Dist: pytest ; extra == 'test'
Requires-Dist: pytest-mock ; extra == 'test'
